expense_tracker/__init__.py
expense_tracker/main.py
expense_tracker/test_draft.py
expense_tracker/test_package.py
expense_tracker/test_suite.py
expense_tracker/expense_management/__init__.py
expense_tracker/expense_management/db_management.py
expense_tracker/expense_management/expense_management_fun_testing.py
expense_tracker/expense_management/expense_operations.py
expense_tracker/expense_management/manager.py
expense_tracker/expense_management/test_expense_manager.py
expense_tracker/expense_management/test_manager.py
expense_tracker/expense_management/test_user_manager.py
expense_tracker/expense_management/user_management.py
expense_tracker/reporting_tools/__init__.py
expense_tracker/reporting_tools/balance_calculation.py
expense_tracker/reporting_tools/report_generation.py
expense_tracker/reporting_tools/test_balance_calculation.py
expense_tracker/reporting_tools/test_graph_draft.py
expense_tracker/reporting_tools/test_report_generation.py
who_owes_who-0.1.0.dist-info/LICENSE.txt
who_owes_who-0.1.0.dist-info/METADATA
who_owes_who-0.1.0.dist-info/WHEEL
who_owes_who-0.1.0.dist-info/top_level.txt
who_owes_who-0.1.0.dist-info/RECORD
