Metadata-Version: 2.1
Name: who-owes-who
Version: 0.1.0
Summary: A Python project for managing expenses and generating reports
Author: Shiqi Zhang, Ernest Wong
Project-URL: Homepage, https://github.com/your-repo/who-owes-who
Project-URL: Issues, https://github.com/your-repo/who-owes-who/issues
Classifier: Development Status :: 4 - Beta
Classifier: Intended Audience :: Developers
Classifier: License :: OSI Approved :: MIT License
Classifier: Programming Language :: Python :: 3.6
Classifier: Programming Language :: Python :: 3.9
Requires-Python: >=3.6
License-File: LICENSE.txt
Provides-Extra: test
Requires-Dist: pytest>=7.0; extra == "test"
Requires-Dist: pytest-cov; extra == "test"
